[{"symbolicName": "IndividualDetails"},
{"symbolicName": "AddressInformation"},
{"symbolicName": "AssetDetails"},
{"symbolicName": "BankStatements"},
{"symbolicName": "ClubsScoities"},
{"symbolicName": "LimitedLiabilityCompany"},
{"symbolicName": "Partnership"},
{"symbolicName": "SoleProprietors"},
{"symbolicName": "InvoiceDetails"},
{"symbolicName": "CRBookDetails"},
{"symbolicName": "TaxStatements"},
{"symbolicName": "InvestigationDetails"},
{"symbolicName": "CRBookDetails"},
{"symbolicName": "BusinessIncomeDetails"},
{"symbolicName": "EmployeeIncomeDetails"},
{"symbolicName": "CFProcess.Workflow.Justification"},
{"symbolicName": "CFProcess.Workflow.VehicleValuation"},
{"symbolicName": "CFProcess.Workflow.CreditBoard"},
{"symbolicName": "CFProcess.Workflow.HigherApproval"},
{"symbolicName": "CFProcess.Workflow.BranchManagerApproval"},
{"symbolicName": "CFProcess.Workflow.InitialPayments"},
{"symbolicName": "CFProcess.Workflow.DeliveryOrder"},
{"symbolicName": "CFProcess.Workflow.PaymentMemo"},
{"symbolicName": "CFProcess.Workflow.BranchManager"},
{"symbolicName": "CFProcess.Workflow.ValuationValuer"},
{"symbolicName": "CFProcess.Workflow.UserValuation"},
{"symbolicName": "CFProcess.Workflow.Agreements"},
{"symbolicName": "CFProcess.Workflow.Insurance"}]
